centered_turtle/__init__.py
centered_turtle-0.3.0.dist-info/licenses/LICENSE
centered_turtle-0.3.0.dist-info/METADATA
centered_turtle-0.3.0.dist-info/WHEEL
centered_turtle-0.3.0.dist-info/top_level.txt
centered_turtle-0.3.0.dist-info/RECORD
